pydyn/asym_1cage.py
pydyn/asym_2cage.py
pydyn/controller.py
pydyn/events.py
pydyn/explicit_blocks.py
pydyn/ext_grid.py
pydyn/interface.py
pydyn/mod_Ybus.py
pydyn/recorder.py
pydyn/run_sim.py
pydyn/sym_order4.py
pydyn/sym_order6a.py
pydyn/sym_order6b.py
pydyn/version.py
pydyn/vsc_average.py
pypower_dynamics-1.1.dist-info/DESCRIPTION.rst
pypower_dynamics-1.1.dist-info/METADATA
pypower_dynamics-1.1.dist-info/metadata.json
pypower_dynamics-1.1.dist-info/RECORD
pypower_dynamics-1.1.dist-info/top_level.txt
pypower_dynamics-1.1.dist-info/WHEEL
