Metadata-Version: 2.0
Name: pypower-dynamics
Version: 1.1
Summary: Time-domain simulation (transient stability) module for PYPOWER
Home-page: https://github.com/susantoj/PYPOWER-Dynamics
Author: Julius Susanto
Author-email: susanto@ieee.org
License: BSD
Platform: UNKNOWN
Classifier: Development Status :: 5 - Production/Stable
Classifier: Environment :: Console
Classifier: Intended Audience :: Developers
Classifier: Intended Audience :: Education
Classifier: Intended Audience :: Science/Research
Classifier: License :: OSI Approved :: BSD License
Classifier: Natural Language :: English
Classifier: Operating System :: OS Independent
Classifier: Programming Language :: Python
Classifier: Programming Language :: Python :: 3
Classifier: Programming Language :: Python :: 3.3
Classifier: Programming Language :: Python :: 3.4
Classifier: Topic :: Scientific/Engineering
